AUTHOR
LICENSE
MANIFEST.in
README.rst
ez_setup.py
setup.cfg
setup.py
doc/Makefile
doc/source/conf.py
doc/source/index.rst
doc/source/installing.rst
doc/source/low_level_1.rst
doc/source/reference_doc.rst
doc/source/tutorial_l1.rst
doc/source/sphinxext/LICENSE.txt
doc/source/sphinxext/MANIFEST.in
doc/source/sphinxext/README.txt
doc/source/sphinxext/numpy_ext/__init__.py
doc/source/sphinxext/numpy_ext/docscrape.py
doc/source/sphinxext/numpy_ext/docscrape_sphinx.py
doc/source/sphinxext/numpy_ext/numpydoc.py
plinkio/Annotation.py
plinkio/Genotype.py
plinkio/__init__.py
plinkio/genodata.py
plinkio/info.py
plinkio/annot/__init__.py
plinkio/annot/assay.py
plinkio/annot/chip.py
plinkio/io/__init__.py
plinkio/io/bplinkread.py
python_plinkio.egg-info/PKG-INFO
python_plinkio.egg-info/SOURCES.txt
python_plinkio.egg-info/dependency_links.txt
python_plinkio.egg-info/requires.txt
python_plinkio.egg-info/top_level.txt