Metadata-Version: 1.1
Name: python-plinkio
Version: 1.0.0
Summary: plinkio
Home-page: https://github.com/neurospin/plinkio.git
Author: PLINKIO developers
Author-email: vincent.frouin@cea.fr
License: CeCILL-B
Platform: OS Independent
Classifier: Development Status :: 5 - Production/Stable
Classifier: Environment :: Console
Classifier: Intended Audience :: Developers
Classifier: Intended Audience :: Science/Research
Classifier: Intended Audience :: Education
Classifier: Operating System :: OS Independent
Classifier: Programming Language :: Python :: 2.7
Classifier: Topic :: Scientific/Engineering
Classifier: Topic :: Utilities
